AUTHORS
CHANGELOG.txt
DESCRIPTION
LICENSE
MANIFEST.in
README.rst
setup.py
calendarium/__init__.py
calendarium/admin.py
calendarium/constants.py
calendarium/forms.py
calendarium/models.py
calendarium/settings.py
calendarium/urls.py
calendarium/utils.py
calendarium/views.py
calendarium/migrations/0001_initial.py
calendarium/migrations/__init__.py
calendarium/south_migrations/0001_initial.py
calendarium/south_migrations/0002_auto__add_field_occurrence_cancelled__chg_field_event_rule.py
calendarium/south_migrations/0003_auto__chg_field_event_end_recurring_period.py
calendarium/south_migrations/0004_auto__chg_field_eventcategory_color.py
calendarium/south_migrations/0005_auto__chg_field_event_created_by.py
calendarium/south_migrations/0006_auto__chg_field_occurrence_created_by.py
calendarium/south_migrations/0007_auto__chg_field_event_category.py
calendarium/south_migrations/0008_auto__add_field_eventcategory_parent.py
calendarium/south_migrations/0009_auto__add_field_eventcategory_slug.py
calendarium/south_migrations/0010_auto__add_field_event_image.py
calendarium/south_migrations/__init__.py
calendarium/static/calendarium/css/calendar.css
calendarium/static/calendarium/css/calendar.less
calendarium/static/calendarium/css/colorpicker.css
calendarium/static/calendarium/img/blank.gif
calendarium/static/calendarium/img/colorpicker_background.png
calendarium/static/calendarium/img/colorpicker_hex.png
calendarium/static/calendarium/img/colorpicker_hsb_b.png
calendarium/static/calendarium/img/colorpicker_hsb_h.png
calendarium/static/calendarium/img/colorpicker_hsb_s.png
calendarium/static/calendarium/img/colorpicker_indic.gif
calendarium/static/calendarium/img/colorpicker_overlay.png
calendarium/static/calendarium/img/colorpicker_rgb_b.png
calendarium/static/calendarium/img/colorpicker_rgb_g.png
calendarium/static/calendarium/img/colorpicker_rgb_r.png
calendarium/static/calendarium/img/colorpicker_select.gif
calendarium/static/calendarium/img/colorpicker_submit.png
django_calendarium.egg-info/PKG-INFO
django_calendarium.egg-info/SOURCES.txt
django_calendarium.egg-info/dependency_links.txt
django_calendarium.egg-info/requires.txt
django_calendarium.egg-info/top_level.txt
