Metadata-Version: 1.0
Name: django-calendarium
Version: 1.3.4
Summary: A reusable Django app to manage and display a calendar in your templates.
